coinstacparsers/__init__.py
coinstacparsers/parsers.py
coinstacparsers-0.0.3.dist-info/LICENSE.txt
coinstacparsers-0.0.3.dist-info/METADATA
coinstacparsers-0.0.3.dist-info/WHEEL
coinstacparsers-0.0.3.dist-info/top_level.txt
coinstacparsers-0.0.3.dist-info/RECORD
